trytond/modules/calendar_scheduling/__init__.py
trytond/modules/calendar_scheduling/caldav.py
trytond/modules/calendar_scheduling/calendar_.py
trytond/modules/calendar_scheduling/res.py
trytond/modules/calendar_scheduling/res.xml
trytond/modules/calendar_scheduling/tryton.cfg
trytond/modules/calendar_scheduling/locale/bg.po
trytond/modules/calendar_scheduling/locale/ca.po
trytond/modules/calendar_scheduling/locale/cs.po
trytond/modules/calendar_scheduling/locale/de.po
trytond/modules/calendar_scheduling/locale/es.po
trytond/modules/calendar_scheduling/locale/es_419.po
trytond/modules/calendar_scheduling/locale/fr.po
trytond/modules/calendar_scheduling/locale/hu_HU.po
trytond/modules/calendar_scheduling/locale/it_IT.po
trytond/modules/calendar_scheduling/locale/ja_JP.po
trytond/modules/calendar_scheduling/locale/lo.po
trytond/modules/calendar_scheduling/locale/lt.po
trytond/modules/calendar_scheduling/locale/nl.po
trytond/modules/calendar_scheduling/locale/pl.po
trytond/modules/calendar_scheduling/locale/pt_BR.po
trytond/modules/calendar_scheduling/locale/ru.po
trytond/modules/calendar_scheduling/locale/sl.po
trytond/modules/calendar_scheduling/locale/zh_CN.po
trytond/modules/calendar_scheduling/tests/__init__.py
trytond/modules/calendar_scheduling/tests/scenario_calendar_scheduling.py
trytond/modules/calendar_scheduling/tests/test_calendar_scheduling.py
trytond/modules/calendar_scheduling/view/user_form.xml
trytond/modules/calendar_scheduling/view/user_form_preferences.xml
trytond_calendar_scheduling-4.2.0.dist-info/DESCRIPTION.rst
trytond_calendar_scheduling-4.2.0.dist-info/METADATA
trytond_calendar_scheduling-4.2.0.dist-info/RECORD
trytond_calendar_scheduling-4.2.0.dist-info/WHEEL
trytond_calendar_scheduling-4.2.0.dist-info/entry_points.txt
trytond_calendar_scheduling-4.2.0.dist-info/metadata.json
trytond_calendar_scheduling-4.2.0.dist-info/top_level.txt
